buildwizard/__init__.py
buildwizard/backend.py
buildwizard/constants.py
buildwizard/core.py
buildwizard/models.py
buildwizard-1.0.0.dist-info/METADATA
buildwizard-1.0.0.dist-info/WHEEL
buildwizard-1.0.0.dist-info/entry_points.txt
buildwizard-1.0.0.dist-info/licenses/LICENSE
buildwizard-1.0.0.dist-info/RECORD
